wingfoil-1.0.0.dist-info/METADATA
wingfoil-1.0.0.dist-info/WHEEL
wingfoil/__init__.py
wingfoil/_wingfoil.cpython-311-darwin.so
wingfoil/stream.py
wingfoil-1.0.0.dist-info/RECORD
