Metadata-Version: 2.4
Name: wingfoil
Version: 1.0.0
Classifier: Programming Language :: Python
Classifier: Programming Language :: Rust
Classifier: Programming Language :: Python :: Implementation :: CPython
Summary: Python bindings for the wingfoil Rust library
Home-Page: https://github.com/wingfoil-io/wingfoil/wingfoil-python
Author: Jake Mitchell
License-Expression: MIT
Requires-Python: >=3.8
Project-URL: homepage, https://github.com/wingfoil-io/wingfoil/
